Metadata-Version: 2.1
Name: j-repo-tools
Version: 0.3.3
Summary: This repo contains a number of tools Open edX uses for working with GitHub repositories.
Home-page: https://github.com/edx/repo-tools
Author: edX
Author-email: oscm@edx.org
License: Apache
Keywords: edx repo tools
Platform: UNKNOWN
Classifier: Environment :: Console
Classifier: Intended Audience :: Developers
Classifier: License :: OSI Approved :: Apache Software License
Requires-Dist: appdirs
Requires-Dist: click
Requires-Dist: lazy
Requires-Dist: github3.py
Requires-Dist: pytest
Requires-Dist: pytest-xdist
Requires-Dist: pyyaml
Requires-Dist: ruamel.yaml
